{
	"description": "项目配置文件",
	"packOptions": {
		"ignore": []
	},
	"setting": {
		"urlCheck": false,
		"es6": true,
		"enhance": false,
		"postcss": true,
		"preloadBackgroundData": false,
		"minified": true,
		"newFeature": true,
		"coverView": true,
		"nodeModules": true,
		"autoAudits": false,
		"showShadowRootInWxmlPanel": true,
		"scopeDataCheck": false,
		"checkInvalidKey": true,
		"checkSiteMap": true,
		"uploadWithSourceMap": true,
		"babelSetting": {
			"ignore": [],
			"disablePlugins": [],
			"outputPath": ""
		}
	},
	"compileType": "miniprogram",
	"libVersion": "2.11.0",
	"appid": "wx66ce3840360010da",
	"projectname": "zhuoxingxiaochengxu",
	"debugOptions": {
		"hidedInDevtools": []
	},
	"isGameTourist": false,
	"simulatorType": "wechat",
	"simulatorPluginLibVersion": {},
	"condition": {
		"search": {
			"current": -1,
			"list": []
		},
		"conversation": {
			"current": -1,
			"list": []
		},
		"plugin": {
			"current": -1,
			"list": []
		},
		"game": {
			"currentL": -1,
			"list": []
		},
		"gamePlugin": {
			"current": -1,
			"list": []
		},
		"miniprogram": {
			"current": -1,
			"list": [
				{
					"id": 0,
					"name": "pages/three/three",
					"pathName": "pages/three/three",
					"query": "",
					"scene": null
				},
				{
					"id": -1,
					"name": "pages/login/login",
					"pathName": "pages/login/login",
					"query": "",
					"scene": null
				},
				{
					"id": -1,
					"name": "pages/my/my",
					"pathName": "pages/my/my",
					"query": "",
					"scene": null
				},
				{
					"id": -1,
					"name": "pages/xiangqing/xiangqing",
					"pathName": "pages/xiangqing/xiangqing",
					"query": "",
					"scene": null
				},
				{
					"id": -1,
					"name": "pages/Order/Order",
					"pathName": "pages/Order/Order",
					"query": "",
					"scene": null
				},
				{
					"id": -1,
					"name": "pages/address/address",
					"pathName": "pages/address/address",
					"query": "",
					"scene": null
				},
				{
					"id": -1,
					"name": "pages/newly/newly",
					"pathName": "pages/newly/newly",
					"query": "",
					"scene": null
				},
				{
					"id": -1,
					"name": "pages/shouquan/shouquan",
					"pathName": "pages/shouquan/shouquan",
					"query": "",
					"scene": null
				},
				{
					"id": -1,
					"name": "pages/denglu/denglu",
					"pathName": "pages/denglu/denglu",
					"query": "",
					"scene": null
				},
				{
					"id": -1,
					"name": "pages/photo/photo",
					"pathName": "pages/photo/photo",
					"query": "",
					"scene": null
				},
				{
					"id": -1,
					"name": "pages/bianji/bianji",
					"pathName": "pages/bianji/bianji",
					"query": "",
					"scene": null
				},
				{
					"id": -1,
					"name": "pages/jifen/jifem",
					"pathName": "pages/jifen/jifem",
					"scene": null
				}
			]
		}
	}
}